holboxai
