Metadata-Version: 2.1
Name: holboxai
Version: 0.12
Summary: HolboxAI package
Home-page: https://github.com/springtownAdmin/holboxai
Author: Sahil Khatri
Author-email: sahil.khatri@holbox.ai
License: MIT
Download-URL: https://github.com/springtownAdmin/holboxai/archive/refs/tags/v_13.tar.gz
Keywords: GenAI,Custom,holbox
Platform: UNKNOWN
Classifier: Development Status :: 3 - Alpha
Classifier: Intended Audience :: Developers
Classifier: Topic :: Software Development :: Build Tools
Classifier: License :: OSI Approved :: MIT License
Classifier: Programming Language :: Python :: 3.8
Classifier: Programming Language :: Python :: 3.9
Classifier: Programming Language :: Python :: 3.10
Classifier: Programming Language :: Python :: 3.11
Classifier: Programming Language :: Python :: 3.12
License-File: LICENSE.txt
